CHANGELOG.md
LICENSE.md
MANIFEST.in
README.md
setup.cfg
setup.py
pystart/__init__.py
pystart/cmd.py
pystart/config.py
pystart/pip_search.py
pystart/progress.py
pystart/setup.cfg.tpl
pystart/username.py
pystart.egg-info/PKG-INFO
pystart.egg-info/SOURCES.txt
pystart.egg-info/dependency_links.txt
pystart.egg-info/entry_points.txt
pystart.egg-info/not-zip-safe
pystart.egg-info/requires.txt
pystart.egg-info/top_level.txt
pystart/changelog/CHANGELOG.md.tpl
pystart/changelog/__init__.py
pystart/changelog/changelog.py
pystart/classifiers/__init__.py
pystart/classifiers/classifiers.py
pystart/classifiers/classifiers.txt
pystart/licenses/APACHEv2-LICENSE.md
pystart/licenses/BSD2CLAUSE-LICENSE.md
pystart/licenses/BSD3CLAUSE-LICENSE.md
pystart/licenses/GG-GPL-LICENSE.md
pystart/licenses/GPLv2-LICENSE.md
pystart/licenses/GPLv3-LICENSE.md
pystart/licenses/ISC-LICENSE.md
pystart/licenses/MIT-LICENSE.md
pystart/licenses/UNLICENSE-LICENSE.md
pystart/licenses/ZLIB-LICENSE.md
pystart/licenses/__init__.py
pystart/licenses/licenses.py
pystart/manifest/MANIFEST.in.tpl
pystart/manifest/__init__.py
pystart/manifest/manifest.py
pystart/readme/README.md.tpl
pystart/readme/__init__.py
pystart/readme/readme.py