Metadata-Version: 1.1
Name: pystart
Version: 0.1.9
Summary: Quick-start for Python packages
Home-page: https://github.com/limix/pystart
Author: Danilo Horta
Author-email: horta@ebi.ac.uk
License: MIT
Download-URL: https://github.com/limix/pystart
Keywords: quick start,package,setup,python
Platform: OS Independent
Platform: Windows
Platform: MacOS
Platform: POSIX
Platform: POSIX :: Linux
Classifier: Development Status :: 4 - Beta
Classifier: Environment :: Console
Classifier: Intended Audience :: Developers
Classifier: License :: OSI Approved :: MIT License
Classifier: Operating System :: OS Independent
Classifier: Programming Language :: Python
